Instruction_Memory.v
module Instruction_Memory(input clk,reset, input[63:0] addr, output[31:0] instr);

    reg [7:0] memory[4095:0];
    integer i;

    initial begin
        for (i = 0; i < 4096; i = i + 1)
                memory[i] = 8'h00;
        $readmemh("../instructions.txt", memory);
    end

    always @(posedge clk) begin
        if (reset) begin
            for (i = 0; i < 4096; i = i + 1)
                memory[i] <= 8'h00;
        end
    end

    assign instr = {memory[addr[11:0]],memory[addr[11:0]+1],memory[addr[11:0]+2],memory[addr[11:0]+3]};

endmodule

Instruction_Memory_tb.v
`timescale 1ns/1ps
`include "Instruction_Memory.v"

module Instruction_Memory_tb;

    reg clk;
    reg reset;
    reg [63:0] addr;
    wire [31:0] instr;

    Instruction_Memory uut(
        .clk(clk),
        .reset(reset),
        .addr(addr),
        .instr(instr)
    );

    initial begin
        clk = 0;
        forever #5 clk = ~clk;
    end

    task run_test;
        input [4:0]  tno;
        input        t_reset;
        input [63:0] t_addr;
        input [31:0] expected;
        begin
            @(negedge clk);
            reset = t_reset;
            addr  = t_addr;

            #6;

            $display("Test %0d", tno);
            $display("Reset       = %b", reset);
            $display("Address     = %0d", addr);
            $display("Instruction = %h", instr);

            if (instr === expected)
                $display("PASS\n");
            else begin
                $display("FAIL");
                $display("Expected    = %h\n", expected);
            end
        end
    endtask

    initial begin
        $dumpfile("Instruction_Memory_tb.vcd");
        $dumpvars(0, Instruction_Memory_tb);

        run_test(1, 1'b0, 64'd0,  32'h00500113);
        run_test(2, 1'b0, 64'd4,  32'h00A00193);
        run_test(3, 1'b0, 64'd8,  32'h003100B3);
        run_test(4, 1'b0, 64'd12, 32'h40310133);

        #20 $finish;
    end
endmodule

build/Instruction_Memory_tb.vcd
$date
	Thu Feb 19 17:55:07 2026
$end
$version
	Icarus Verilog
$end
$timescale
	1ps
$end
$scope module Instruction_Memory_tb $end
$var wire 32 ! instr [31:0] $end
$var reg 64 " addr [63:0] $end
$var reg 1 # clk $end
$var reg 1 $ reset $end
$scope module uut $end
$var wire 64 % addr [63:0] $end
$var wire 1 # clk $end
$var wire 1 $ reset $end
$var wire 32 & instr [31:0] $end
$var integer 32 ' i [31:0] $end
$upscope $end
$scope task run_test $end
$var reg 32 ( expected [31:0] $end
$var reg 64 ) t_addr [63:0] $end
$var reg 1 * t_reset $end
$var reg 5 + tno [4:0] $end
$upscope $end
$upscope $end
$enddefinitions $end
$comment Show the parameter values. $end
$dumpall
$end
#0
$dumpvars
b1 +
0*
b0 )
b10100000000000100010011 (
b1000000000000 '
bx &
bx %
x$
0#
bx "
bx !
$end
#5000
1#
#10000
b10100000000000100010011 !
b10100000000000100010011 &
b0 "
b0 %
0$
0#
#15000
1#
#16000
b101000000000000110010011 (
b100 )
b10 +
#20000
b101000000000000110010011 !
b101000000000000110010011 &
b100 "
b100 %
0#
#25000
1#
#26000
b1100010000000010110011 (
b1000 )
b11 +
#30000
b1100010000000010110011 !
b1100010000000010110011 &
b1000 "
b1000 %
0#
#35000
1#
#36000
b1000000001100010000000100110011 (
b1100 )
b100 +
#40000
b1000000001100010000000100110011 !
b1000000001100010000000100110011 &
b1100 "
b1100 %
0#
